viperdb/__init__.py
viperdb/db.py
viperdb-1.0.0.dist-info/LICENSE
viperdb-1.0.0.dist-info/METADATA
viperdb-1.0.0.dist-info/WHEEL
viperdb-1.0.0.dist-info/top_level.txt
viperdb-1.0.0.dist-info/RECORD
