Metadata-Version: 2.1
Name: viperdb
Version: 1.0.0
Summary: A tiny log-structured key-value database written in pure Python
Home-page: https://github.com/ostafen/viperdb
Author: Real Python
Author-email: stefano.scafiti96@gmail.com
License: MIT
Platform: UNKNOWN
Classifier: License :: OSI Approved :: MIT License
Classifier: Programming Language :: Python :: 3
Classifier: Programming Language :: Python :: 3.8
